[1,["755RMxrKJJPpBXH5COMT4t"],0,[["sp.SkeletonData",["_name","_atlasText","textureNames","_skeletonJson","textures"],-1,3]],[[0,0,1,2,3,4,5]],[[0,"shou","\nshou.png\nsize: 1024,256\nformat: RGBA4444\nfilter: Linear,Linear\nrepeat: none\nshou0001\n  rotate: false\n  xy: 2, 2\n  size: 130, 145\n  orig: 130, 145\n  offset: 0, 0\n  index: -1\nshou0002\n  rotate: false\n  xy: 134, 4\n  size: 130, 143\n  orig: 130, 143\n  offset: 0, 0\n  index: -1\nshou0003\n  rotate: false\n  xy: 266, 8\n  size: 130, 139\n  orig: 130, 139\n  offset: 0, 0\n  index: -1\nshou0004\n  rotate: false\n  xy: 398, 10\n  size: 130, 137\n  orig: 130, 137\n  offset: 0, 0\n  index: -1\nshou0005\n  rotate: false\n  xy: 530, 13\n  size: 129, 134\n  orig: 129, 134\n  offset: 0, 0\n  index: -1\nshou0006\n  rotate: false\n  xy: 661, 15\n  size: 129, 132\n  orig: 129, 132\n  offset: 0, 0\n  index: -1\n",["shou.png"],{"skeleton":{"hash":"kbvNB/1A6DBm8eTWhGRgkPwN4I8","spine":"3.6.53","width":129,"height":132},"bones":[{"name":"root"},{"name":"shou0001","parent":"root","x":27.08,"y":21.84}],"slots":[{"name":"shou0001","bone":"shou0001","attachment":"shou0006"}],"skins":{"default":{"shou0001":{"shou0001":{"x":-29.17,"y":52.23,"width":130,"height":145},"shou0002":{"x":-29.17,"y":51.23,"width":130,"height":143},"shou0003":{"x":-30.17,"y":50.23,"width":130,"height":139},"shou0004":{"x":-30.17,"y":49.23,"width":130,"height":137},"shou0005":{"x":-30.67,"y":48.73,"width":129,"height":134},"shou0006":{"x":-30.67,"y":47.73,"width":129,"height":132}}}},"animations":{"shou":{"slots":{"shou0001":{"attachment":[{"time":0,"name":"shou0001"},{"time":0.1,"name":"shou0002"},{"time":0.1333,"name":"shou0003"},{"time":0.1667,"name":"shou0004"},{"time":0.2,"name":"shou0005"},{"time":0.2333,"name":"shou0006"},{"time":0.3667,"name":"shou0006"}]}}}}},[0]]],0,0,[0],[-1],[0]]